MANIFEST.in
README.md
setup.py
sxysdk/__init__.py
sxysdk.egg-info/PKG-INFO
sxysdk.egg-info/SOURCES.txt
sxysdk.egg-info/dependency_links.txt
sxysdk.egg-info/not-zip-safe
sxysdk.egg-info/requires.txt
sxysdk.egg-info/top_level.txt
sxysdk/Database/OracleDB.py
sxysdk/Database/__init__.py
sxysdk/Examples/OracleDB_Test_Script.py
sxysdk/Examples/__init__.py
sxysdk/FileCopy/FileCopy.py
sxysdk/FileCopy/__init__.py
sxysdk/IPMI/IPMI.py
sxysdk/IPMI/__init__.py
sxysdk/PsExc/PsExc.py
sxysdk/PsExc/__init__.py
sxysdk/SSH/SSH.py
sxysdk/SSH/__init__.py
sxysdk/Time/Time.py
sxysdk/Time/__init__.py
sxysdk/Tools/PSTools/Eula.txt
sxysdk/Tools/PSTools/PsExec.exe
sxysdk/Tools/PSTools/PsExec64.exe
sxysdk/Tools/PSTools/PsGetsid.exe
sxysdk/Tools/PSTools/PsGetsid64.exe
sxysdk/Tools/PSTools/PsInfo.exe
sxysdk/Tools/PSTools/PsInfo64.exe
sxysdk/Tools/PSTools/PsLoggedon.exe
sxysdk/Tools/PSTools/PsLoggedon64.exe
sxysdk/Tools/PSTools/PsService.exe
sxysdk/Tools/PSTools/PsService64.exe
sxysdk/Tools/PSTools/Pstools.chm
sxysdk/Tools/PSTools/psfile.exe
sxysdk/Tools/PSTools/psfile64.exe
sxysdk/Tools/PSTools/pskill.exe
sxysdk/Tools/PSTools/pskill64.exe
sxysdk/Tools/PSTools/pslist.exe
sxysdk/Tools/PSTools/pslist64.exe
sxysdk/Tools/PSTools/psloglist.exe
sxysdk/Tools/PSTools/pspasswd.exe
sxysdk/Tools/PSTools/pspasswd64.exe
sxysdk/Tools/PSTools/psping.exe
sxysdk/Tools/PSTools/psping64.exe
sxysdk/Tools/PSTools/psshutdown.exe
sxysdk/Tools/PSTools/pssuspend.exe
sxysdk/Tools/PSTools/pssuspend64.exe
sxysdk/Tools/PSTools/psversion.txt
sxysdk/Tools/TestTools/Dbgview.exe
sxysdk/Tools/TestTools/DiskTest.exe
sxysdk/Tools/TestTools/RemoveRegInfo.bat
sxysdk/Tools/TestTools/RunDiskTest.bat
sxysdk/Tools/TestTools/StartDbgview.bat
sxysdk/Tools/TestTools/TimeSync.bat
sxysdk/Tools/TestTools/osrbang.exe
sxysdk/Tools/bmc/DSM_BMU_SOLProxy32.exe
sxysdk/Tools/bmc/cygcrypto-0.9.8.dll
sxysdk/Tools/bmc/cygwin1.dll
sxysdk/Tools/bmc/dcwipm32.dll
sxysdk/Tools/bmc/ipmish.exe
sxysdk/Tools/bmc/ipmitool.exe
sxysdk/Tools/bmc/readme.txt
sxysdk/Tools/bmc/solproxy.cfg
sxysdk/WinCmd/WindowsCMD.py
sxysdk/WinCmd/__init__.py
sxysdk/vSphereCLI/__init__.py
sxysdk/vSphereCLI/vSphereCLI.py