Metadata-Version: 1.1
Name: sxysdk
Version: 0.0.20
Summary: sxy python sdk
Home-page: https://github.com/shenxiaoyang/sxysdk-python.git
Author: shenxiaoyang
Author-email: 380944919@infocore.cn
License: GPLv3
Download-URL: https://github.com/shenxiaoyang/sxysdk-python.git
Keywords: sdk
Platform: UNKNOWN
